multi_purpose_arduino_controller/__init__.py
multi_purpose_arduino_controller/python_communicator.py
multi_purpose_arduino_controller/arduino_controller/__init__.py
multi_purpose_arduino_controller/arduino_controller/api.py
multi_purpose_arduino_controller/arduino_controller/arduino_variable.py
multi_purpose_arduino_controller/arduino_controller/datalogger.py
multi_purpose_arduino_controller/arduino_controller/parseboards.py
multi_purpose_arduino_controller/arduino_controller/portcommand.py
multi_purpose_arduino_controller/arduino_controller/portrequest.py
multi_purpose_arduino_controller/arduino_controller/serialport.py
multi_purpose_arduino_controller/arduino_controller/basicboard/__init__.py
multi_purpose_arduino_controller/arduino_controller/basicboard/arduino_data.py
multi_purpose_arduino_controller/arduino_controller/basicboard/board.py
multi_purpose_arduino_controller/arduino_controller/basicboard/defaultcodes.py
multi_purpose_arduino_controller/arduino_controller/basicboard/ino_creator.py
multi_purpose_arduino_controller/arduino_controller/basicboard/pin.py
multi_purpose_arduino_controller/arduino_controller/serialreader/__init__.py
multi_purpose_arduino_controller/arduino_controller/serialreader/serialdetector.py
multi_purpose_arduino_controller/arduino_controller/serialreader/serialreader.py
multi_purpose_arduino_controller/controll_server/__init__.py
multi_purpose_arduino_controller/controll_server/manage.py
multi_purpose_arduino_controller/controll_server/board_controller/__init__.py
multi_purpose_arduino_controller/controll_server/board_controller/admin.py
multi_purpose_arduino_controller/controll_server/board_controller/apps.py
multi_purpose_arduino_controller/controll_server/board_controller/board_controller_api.py
multi_purpose_arduino_controller/controll_server/board_controller/models.py
multi_purpose_arduino_controller/controll_server/board_controller/tests.py
multi_purpose_arduino_controller/controll_server/board_controller/urls.py
Multi_Purpose_Arduino_Controller-0.1.1560516432.dist-info/METADATA
Multi_Purpose_Arduino_Controller-0.1.1560516432.dist-info/WHEEL
Multi_Purpose_Arduino_Controller-0.1.1560516432.dist-info/top_level.txt
Multi_Purpose_Arduino_Controller-0.1.1560516432.dist-info/RECORD
