Metadata-Version: 2.1
Name: Multi-Purpose-Arduino-Controller
Version: 0.1.1560516432
Summary: Controll Arduino modules
Home-page: https://github.com/JulianKimmig/multi_purpose_arduino_controller
Author: Julian Kimmig
Author-email: julian-kimmig@gmxREADME.md.net
License: UNKNOWN
Platform: UNKNOWN
Classifier: Programming Language :: Python :: 3
Classifier: License :: OSI Approved :: MIT License
Classifier: Operating System :: OS Independent
Requires-Dist: numpy
Requires-Dist: pandas
Requires-Dist: pyserial
Requires-Dist: django-bootstrap4
Requires-Dist: custom-accounts-django
Requires-Dist: django
Requires-Dist: django-glrm
